pulumi_formal/__init__.py
pulumi_formal/_inputs.py
pulumi_formal/_utilities.py
pulumi_formal/connector.py
pulumi_formal/connector_configuration.py
pulumi_formal/connector_hostname.py
pulumi_formal/connector_listener.py
pulumi_formal/connector_listener_link.py
pulumi_formal/connector_listener_rule.py
pulumi_formal/data_discovery.py
pulumi_formal/data_domain.py
pulumi_formal/data_label.py
pulumi_formal/encryption_key.py
pulumi_formal/get_group.py
pulumi_formal/get_resource.py
pulumi_formal/group.py
pulumi_formal/group_user_link.py
pulumi_formal/integration_bi.py
pulumi_formal/integration_cloud.py
pulumi_formal/integration_data_catalog.py
pulumi_formal/integration_log.py
pulumi_formal/integration_mdm.py
pulumi_formal/integration_mfa.py
pulumi_formal/inventory_object_data_label_link.py
pulumi_formal/log_configuration.py
pulumi_formal/native_user.py
pulumi_formal/native_user_link.py
pulumi_formal/outputs.py
pulumi_formal/permission.py
pulumi_formal/policy.py
pulumi_formal/policy_data_loader.py
pulumi_formal/provider.py
pulumi_formal/pulumi-plugin.json
pulumi_formal/py.typed
pulumi_formal/resource.py
pulumi_formal/resource_classifier_configuration.py
pulumi_formal/resource_health_check.py
pulumi_formal/resource_hostname.py
pulumi_formal/resource_tls_configuration.py
pulumi_formal/satellite.py
pulumi_formal/sidecar.py
pulumi_formal/sidecar_resource_link.py
pulumi_formal/space.py
pulumi_formal/tracker.py
pulumi_formal/user.py
pulumi_formal/config/__init__.py
pulumi_formal/config/__init__.pyi
pulumi_formal/config/vars.py
pulumi_formal-1.0.3.dist-info/METADATA
pulumi_formal-1.0.3.dist-info/WHEEL
pulumi_formal-1.0.3.dist-info/top_level.txt
pulumi_formal-1.0.3.dist-info/RECORD
