Metadata-Version: 2.4
Name: pulumi_formal
Version: 1.0.3
Summary: A Pulumi package for creating and managing Formal resources.
License: MPL-2.0
Project-URL: Homepage, https://joinformal.com
Project-URL: Repository, https://github.com/formalco/pulumi-formal
Keywords: formal,category/cloud,category/database,category/network
Requires-Python: >=3.9
Requires-Dist: parver>=0.2.1
Requires-Dist: pulumi<4.0.0,>=3.165.0
Requires-Dist: semver>=2.8.1
Requires-Dist: typing-extensions<5,>=4.11; python_version < "3.11"
